[
  {
    "Id": 113482,
    "Nome": "ANTONIO DA CONCEICAO SANTOS",
    "Cargo": "ELETRICISTA",
    "Regional": "ECOSAMPA Operação Geral",
    "Gerente": "João Sales",
    "Departamento": "MECANICA",
    "Total_Fev": "-40,75",
    "Total_Mar": "-41,58",
    "Total_Abr": "-48,40",
    "Total_Mai": "-53,53",
    "Total_Jun": "-58,07",
    "Total_Jul": "-61,58",
    "Total_Ago": "-77,43"
  },
  {
    "Id": 112667,
    "Nome": "LEONARDO NASCIMENTO ALVES",
    "Cargo": "LAVADOR",
    "Regional": "ECOSAMPA Operação Geral",
    "Gerente": "João Sales",
    "Departamento": "MECANICA",
    "Total_Fev": "-77,50",
    "Total_Mar": "-82,13",
    "Total_Abr": "-88,13",
    "Total_Mai": "-84,18",
    "Total_Jun": "-79,08",
    "Total_Jul": "-79,38",
    "Total_Ago": "-76,93"
  },
  {
    "Id": 114004,
    "Nome": "VANILTON DOS SANTOS",
    "Cargo": "SOLDADOR",
    "Regional": "ECOSAMPA Operação Geral",
    "Gerente": "João Sales",
    "Departamento": "MECANICA",
    "Total_Fev": "-24,45",
    "Total_Mar": "-27,93",
    "Total_Abr": "-18,02",
    "Total_Mai": "-49,25",
    "Total_Jun": "-53,00",
    "Total_Jul": "-56,50",
    "Total_Ago": "-59,63"
  },
  {
    "Id": 112893,
    "Nome": "WILLIAM ARAUJO DA SILVA",
    "Cargo": "FISCAL DE TURMA PLENO",
    "Regional": "ECOSAMPA Santo Amaro",
    "Gerente": "Gustavo",
    "Departamento": "OPERAÇÃO",
    "Total_Fev": "-26,07",
    "Total_Mar": "-27,25",
    "Total_Abr": "-31,02",
    "Total_Mai": "-31,02",
    "Total_Jun": "-31,02",
    "Total_Jul": "-31,02",
    "Total_Ago": "-35,27"
  },
  {
    "Id": 114538,
    "Nome": "FABIANO ANSALDI DOMINGOS",
    "Cargo": "ENCARREGADO DE TURMA",
    "Regional": "ECOSAMPA Santo Amaro",
    "Gerente": "Gustavo",
    "Departamento": "OPERAÇÃO",
    "Total_Fev": "-10,82",
    "Total_Mar": "-15,97",
    "Total_Abr": "-20,50",
    "Total_Mai": "-24,97",
    "Total_Jun": "-26,15",
    "Total_Jul": "-25,07",
    "Total_Ago": "-30,45"
  },
  {
    "Id": 113768,
    "Nome": "LEONARDO FRANCISCO DOS SANTOS",
    "Cargo": "FISCAL DE TURMA PLENO",
    "Regional": "ECOSAMPA Santo Amaro",
    "Gerente": "Gustavo",
    "Departamento": "OPERAÇÃO",
    "Total_Fev": "-9,95",
    "Total_Mar": "-10,83",
    "Total_Abr": "-12,95",
    "Total_Mai": "-17,43",
    "Total_Jun": "-13,80",
    "Total_Jul": "-13,32",
    "Total_Ago": "-25,78"
  },
  {
    "Id": 112376,
    "Nome": "WILTON SOUSA SILVA",
    "Cargo": "LAVADOR",
    "Regional": "ECOSAMPA Operação Geral",
    "Gerente": "João Sales",
    "Departamento": "MECANICA",
    "Total_Fev": "-11,03",
    "Total_Mar": "-11,03",
    "Total_Abr": "-11,80",
    "Total_Mai": "-19,52",
    "Total_Jun": "-26,45",
    "Total_Jul": "-26,38",
    "Total_Ago": "-24,70"
  },
  {
    "Id": 125192,
    "Nome": "WILLIAN DA SILVA SANTOS",
    "Cargo": "ECOSAMPA Santo Amaro",
    "Regional": "FISCAL DE TURMA PLENO",
    "Gerente": "OPERAÇÃO",
    "Departamento": "GUSTAVO",
    "Total_Fev": "-",
    "Total_Mar": "-",
    "Total_Abr": "-",
    "Total_Mai": "-",
    "Total_Jun": "-",
    "Total_Jul": "-",
    "Total_Ago": "-20,05"
  },
  {
    "Id": 114506,
    "Nome": "FABIO JOSE DOS SANTOS",
    "Cargo": "PEDREIRO",
    "Regional": "ECOSAMPA Operação Geral",
    "Gerente": "Gustavo",
    "Departamento": "PREDIAL",
    "Total_Fev": "-16,23",
    "Total_Mar": "-23,85",
    "Total_Abr": "-24,05",
    "Total_Mai": "-26,98",
    "Total_Jun": "-27,50",
    "Total_Jul": "-17,90",
    "Total_Ago": "-19,68"
  },
  {
    "Id": 113490,
    "Nome": "ANTONIO DE LIMA RIBEIRO",
    "Cargo": "ECOSAMPA Operação Geral",
    "Regional": "MECANICO II",
    "Gerente": "MECANICA",
    "Departamento": "JOÃO PAULO",
    "Total_Fev": "-",
    "Total_Mar": "-",
    "Total_Abr": "-",
    "Total_Mai": "-",
    "Total_Jun": "-",
    "Total_Jul": "-21,95",
    "Total_Ago": "-19,12"
  },
  {
    "Id": 112892,
    "Nome": "LUIS CARLOS MATOS DE ALMEIDA",
    "Cargo": "ECOSAMPA Operação Geral",
    "Regional": "AUXILIAR DE TRAFEGO",
    "Gerente": "TRAFEGO",
    "Departamento": "GUSTAVO",
    "Total_Fev": "-",
    "Total_Mar": "-",
    "Total_Abr": "-",
    "Total_Mai": "-",
    "Total_Jun": "-",
    "Total_Jul": "-",
    "Total_Ago": "-18,23"
  },
  {
    "Id": 113763,
    "Nome": "BILLY JOE ZAKARIAN",
    "Cargo": "ECOSAMPA Operação Geral",
    "Regional": "ENCARREGADO DE TRAFEGO II",
    "Gerente": "TRAFEGO",
    "Departamento": "GUSTAVO",
    "Total_Fev": "-",
    "Total_Mar": "-",
    "Total_Abr": "-",
    "Total_Mai": "-",
    "Total_Jun": "-",
    "Total_Jul": "-",
    "Total_Ago": "-14,65"
  },
  {
    "Id": 121684,
    "Nome": "WALKER MINANCIAM DA SILVA",
    "Cargo": "AUXILIAR DE CONTROLE OPERACIONAL",
    "Regional": "ECOSAMPA Operação Geral",
    "Gerente": "João Sales",
    "Departamento": "PLANEJAMENTO",
    "Total_Fev": "-",
    "Total_Mar": "-",
    "Total_Abr": "-",
    "Total_Mai": "-",
    "Total_Jun": "-8,60",
    "Total_Jul": "-12,67",
    "Total_Ago": "-13,77"
  },
  {
    "Id": 125199,
    "Nome": "RAQUEL LARISSA DA SILVA DIAS",
    "Cargo": "ECOSAMPA Administração",
    "Regional": "AUXILIAR ADMINISTRATIVO",
    "Gerente": "ADM/FINANCEIRO",
    "Departamento": "WILSON",
    "Total_Fev": "-",
    "Total_Mar": "-",
    "Total_Abr": "-",
    "Total_Mai": "-",
    "Total_Jun": "-",
    "Total_Jul": "-",
    "Total_Ago": "-13,73"
  },
  {
    "Id": 118993,
    "Nome": "MARCOS MARCIO ROCHA SANTOS",
    "Cargo": "SOLDADOR",
    "Regional": "ECOSAMPA Operação Geral",
    "Gerente": "João Sales",
    "Departamento": "MECANICA",
    "Total_Fev": "-8,62",
    "Total_Mar": "-8,08",
    "Total_Abr": "-8,00",
    "Total_Mai": "-8,00",
    "Total_Jun": "-10,70",
    "Total_Jul": "-11,62",
    "Total_Ago": "-13,17"
  },
  {
    "Id": 112745,
    "Nome": "FABRICIO DA COSTA GOMES",
    "Cargo": "LAVADOR",
    "Regional": "ECOSAMPA Operação Geral",
    "Gerente": "João Sales",
    "Departamento": "MECANICA",
    "Total_Fev": "-",
    "Total_Mar": "-",
    "Total_Abr": "-",
    "Total_Mai": "-10,68",
    "Total_Jun": "-10,62",
    "Total_Jul": "-10,72",
    "Total_Ago": "-12,40"
  },
  {
    "Id": 113118,
    "Nome": "JOSE ILARIO DOS SANTOS",
    "Cargo": "BORRACHEIRO II",
    "Regional": "ECOSAMPA Operação Geral",
    "Gerente": "João Sales",
    "Departamento": "MECANICA",
    "Total_Fev": "-11,43",
    "Total_Mar": "-11,40",
    "Total_Abr": "-11,30",
    "Total_Mai": "-11,10",
    "Total_Jun": "-10,85",
    "Total_Jul": "-10,08",
    "Total_Ago": "-10,52"
  },
  {
    "Id": 113729,
    "Nome": "JOICE MARIA DO NASCIMENTO",
    "Cargo": "ECOSAMPA Operação Geral",
    "Regional": "FAXINEIRO(A)",
    "Gerente": "ADM/FINANCEIRO",
    "Departamento": "WILSON",
    "Total_Fev": "-",
    "Total_Mar": "-",
    "Total_Abr": "-",
    "Total_Mai": "-",
    "Total_Jun": "-",
    "Total_Jul": "-",
    "Total_Ago": "-8,70"
  },
  {
    "Id": "",
    "Nome": "",
    "Cargo": "",
    "Regional": "",
    "Gerente": "",
    "Departamento": "",
    "Total_Fev": "",
    "Total_Mar": "",
    "Total_Abr": "",
    "Total_Mai": "",
    "Total_Jun": "",
    "Total_Jul": "",
    "Total_Ago": ""
  }
]